zensols/latidx/resources/app.conf
zensols/latidx/resources/obj.yml
zensols/latidx/__init__.py
zensols/latidx/app.py
zensols/latidx/cli.py
zensols/latidx/domain.py
zensols/latidx/file.py
zensols/latidx/index.py
zensols_latidx-0.2.0.dist-info/METADATA
zensols_latidx-0.2.0.dist-info/WHEEL
zensols_latidx-0.2.0.dist-info/entry_points.txt
zensols_latidx-0.2.0.dist-info/licenses/LICENSE.md
zensols_latidx-0.2.0.dist-info/RECORD
