Metadata-Version: 2.3
Name: zensols_latidx
Version: 0.2.0
Summary: TODO
Project-URL: Homepage, https://github.com/plandes/latidx
Project-URL: Documentation, https://plandes.github.io/latidx
Project-URL: Repository, https://github.com/plandes/latidx.git
Project-URL: Issues, https://github.com/plandes/latidx/issues
Project-URL: Changelog, https://github.com/plandes/latidx/blob/master/CHANGELOG.md
Author-email: Paul Landes <landes@mailc.net>
License: MIT
Keywords: tooling
Requires-Python: <3.15,>=3.11
Requires-Dist: asciitree~=0.3.3
Requires-Dist: pylatexenc~=2.10
Requires-Dist: zensols-util~=1.16.2
